datapungibea/_NIPAIndentations.py
datapungibea/__init__.py
datapungibea/api.py
datapungibea/drivers.py
datapungibea/generalSettings.py
datapungibea/utils.py
datapungibea/vintage.py
datapungibea/config/CFGindentations.py
datapungibea/config/CFGnipaSummary.py
datapungibea/config/__init__.py
datapungibea/config/pkgConfig.yaml
datapungibea/config/userSettings.json
datapungibea/tests/__init__.py
datapungibea/tests/conftest.py
datapungibea/tests/main.py
datapungibea/tests/test_drivers.py
datapungibea/tests/test_driversCI.py
datapungibea-1.0.2.dist-info/LICENSE
datapungibea-1.0.2.dist-info/WHEEL
datapungibea-1.0.2.dist-info/METADATA
datapungibea-1.0.2.dist-info/RECORD
